{
"meta":{"test_sets":[],"test_metrics":[],"learn_metrics":[{"best_value":"Min","name":"Logloss"}],"launch_mode":"Train","parameters":"","iteration_count":100,"learn_sets":["learn"],"name":"experiment"},
"iterations":[
{"learn":[0.6633492311],"iteration":0,"passed_time":0.04569090395,"remaining_time":4.523399491},
{"learn":[0.6381965522],"iteration":1,"passed_time":0.08216789389,"remaining_time":4.026226801},
{"learn":[0.6132531447],"iteration":2,"passed_time":0.1213573898,"remaining_time":3.923888938},
{"learn":[0.593934328],"iteration":3,"passed_time":0.1687880623,"remaining_time":4.050913495},
{"learn":[0.5766116094],"iteration":4,"passed_time":0.2085381066,"remaining_time":3.962224026},
{"learn":[0.556970309],"iteration":5,"passed_time":0.2509411449,"remaining_time":3.93141127},
{"learn":[0.543164112],"iteration":6,"passed_time":0.2521725135,"remaining_time":3.350291964},
{"learn":[0.5289722327],"iteration":7,"passed_time":0.289042351,"remaining_time":3.323987037},
{"learn":[0.5145347086],"iteration":8,"passed_time":0.3248857443,"remaining_time":3.284955859},
{"learn":[0.5019088311],"iteration":9,"passed_time":0.3596201319,"remaining_time":3.236581187},
{"learn":[0.4875206374],"iteration":10,"passed_time":0.394481311,"remaining_time":3.191712426},
{"learn":[0.4789772933],"iteration":11,"passed_time":0.4295566499,"remaining_time":3.150082099},
{"learn":[0.4694274817],"iteration":12,"passed_time":0.4706468334,"remaining_time":3.149713423},
{"learn":[0.4617881827],"iteration":13,"passed_time":0.5047216888,"remaining_time":3.100433231},
{"learn":[0.4533898895],"iteration":14,"passed_time":0.5407407244,"remaining_time":3.064197438},
{"learn":[0.4447178261],"iteration":15,"passed_time":0.5739714887,"remaining_time":3.013350316},
{"learn":[0.4387113373],"iteration":16,"passed_time":0.6076128089,"remaining_time":2.966580185},
{"learn":[0.4328851012],"iteration":17,"passed_time":0.6418885998,"remaining_time":2.924159177},
{"learn":[0.4270214623],"iteration":18,"passed_time":0.6787567354,"remaining_time":2.893647135},
{"learn":[0.4208629941],"iteration":19,"passed_time":0.7129855988,"remaining_time":2.851942395},
{"learn":[0.4155083376],"iteration":20,"passed_time":0.7480499885,"remaining_time":2.814092814},
{"learn":[0.409928292],"iteration":21,"passed_time":0.7824066341,"remaining_time":2.773987157},
{"learn":[0.4059491398],"iteration":22,"passed_time":0.8164157797,"remaining_time":2.733218045},
{"learn":[0.4008286467],"iteration":23,"passed_time":0.8292996899,"remaining_time":2.626115685},
{"learn":[0.3964938029],"iteration":24,"passed_time":0.8652624014,"remaining_time":2.595787204},
{"learn":[0.3928663005],"iteration":25,"passed_time":0.9015239203,"remaining_time":2.565875773},
{"learn":[0.3897721348],"iteration":26,"passed_time":0.9371527445,"remaining_time":2.533783346},
{"learn":[0.3822747877],"iteration":27,"passed_time":0.9723523511,"remaining_time":2.500334617},
{"learn":[0.3789674531],"iteration":28,"passed_time":1.004363587,"remaining_time":2.458959126},
{"learn":[0.3750909277],"iteration":29,"passed_time":1.037921117,"remaining_time":2.42181594},
{"learn":[0.3718038743],"iteration":30,"passed_time":1.074816798,"remaining_time":2.392334163},
{"learn":[0.3686589498],"iteration":31,"passed_time":1.110185426,"remaining_time":2.359144031},
{"learn":[0.3653622425],"iteration":32,"passed_time":1.145749782,"remaining_time":2.326219254},
{"learn":[0.3631671661],"iteration":33,"passed_time":1.157869613,"remaining_time":2.24762925},
{"learn":[0.3602993863],"iteration":34,"passed_time":1.177703542,"remaining_time":2.18716372},
{"learn":[0.3573271652],"iteration":35,"passed_time":1.204766923,"remaining_time":2.141807864},
{"learn":[0.3548521401],"iteration":36,"passed_time":1.225872086,"remaining_time":2.087295715},
{"learn":[0.3526281178],"iteration":37,"passed_time":1.244885202,"remaining_time":2.031128488},
{"learn":[0.3500552573],"iteration":38,"passed_time":1.264804994,"remaining_time":1.978284734},
{"learn":[0.3474637611],"iteration":39,"passed_time":1.282782367,"remaining_time":1.924173551},
{"learn":[0.3441661993],"iteration":40,"passed_time":1.300570427,"remaining_time":1.871552565},
{"learn":[0.3418237621],"iteration":41,"passed_time":1.317404409,"remaining_time":1.819272755},
{"learn":[0.3393813256],"iteration":42,"passed_time":1.334783153,"remaining_time":1.769363715},
{"learn":[0.3367420834],"iteration":43,"passed_time":1.36763862,"remaining_time":1.740630971},
{"learn":[0.334550612],"iteration":44,"passed_time":1.400330323,"remaining_time":1.711514839},
{"learn":[0.3309529364],"iteration":45,"passed_time":1.432404975,"remaining_time":1.681518883},
{"learn":[0.3285666493],"iteration":46,"passed_time":1.4670362,"remaining_time":1.654317417},
{"learn":[0.3268329712],"iteration":47,"passed_time":1.500109401,"remaining_time":1.625118518},
{"learn":[0.3244808323],"iteration":48,"passed_time":1.532460375,"remaining_time":1.595009778},
{"learn":[0.3227699363],"iteration":49,"passed_time":1.563919517,"remaining_time":1.563919517},
{"learn":[0.3211833298],"iteration":50,"passed_time":1.596185498,"remaining_time":1.533589989},
{"learn":[0.3187118118],"iteration":51,"passed_time":1.627212288,"remaining_time":1.502042112},
{"learn":[0.3173584389],"iteration":52,"passed_time":1.660694262,"remaining_time":1.472691138},
{"learn":[0.3158010241],"iteration":53,"passed_time":1.693365782,"remaining_time":1.442496777},
{"learn":[0.3137936427],"iteration":54,"passed_time":1.726553083,"remaining_time":1.412634341},
{"learn":[0.3117806819],"iteration":55,"passed_time":1.758281536,"remaining_time":1.381506921},
{"learn":[0.310390391],"iteration":56,"passed_time":1.79156026,"remaining_time":1.351527915},
{"learn":[0.308511651],"iteration":57,"passed_time":1.824533474,"remaining_time":1.321213895},
{"learn":[0.3054131938],"iteration":58,"passed_time":1.856614166,"remaining_time":1.290189505},
{"learn":[0.3037986882],"iteration":59,"passed_time":1.890555047,"remaining_time":1.260370031},
{"learn":[0.3026761765],"iteration":60,"passed_time":1.92307975,"remaining_time":1.229510004},
{"learn":[0.3017048115],"iteration":61,"passed_time":1.956059816,"remaining_time":1.198875371},
{"learn":[0.3008115866],"iteration":62,"passed_time":1.990096098,"remaining_time":1.168786597},
{"learn":[0.2989465989],"iteration":63,"passed_time":2.023628306,"remaining_time":1.138290922},
{"learn":[0.297816395],"iteration":64,"passed_time":2.05629098,"remaining_time":1.107233605},
{"learn":[0.2965879841],"iteration":65,"passed_time":2.087800978,"remaining_time":1.075533837},
{"learn":[0.2944397638],"iteration":66,"passed_time":2.121280117,"remaining_time":1.04480961},
{"learn":[0.2927211457],"iteration":67,"passed_time":2.153627956,"remaining_time":1.013471979},
{"learn":[0.2913740164],"iteration":68,"passed_time":2.185797486,"remaining_time":0.9820249574},
{"learn":[0.2903264997],"iteration":69,"passed_time":2.219184119,"remaining_time":0.9510789081},
{"learn":[0.288743359],"iteration":70,"passed_time":2.25370997,"remaining_time":0.9205294242},
{"learn":[0.2868365278],"iteration":71,"passed_time":2.285986789,"remaining_time":0.8889948625},
{"learn":[0.2850002111],"iteration":72,"passed_time":2.318732253,"remaining_time":0.8576132989},
{"learn":[0.2841135104],"iteration":73,"passed_time":2.352191096,"remaining_time":0.8264455204},
{"learn":[0.2831875948],"iteration":74,"passed_time":2.384792549,"remaining_time":0.7949308496},
{"learn":[0.2806465627],"iteration":75,"passed_time":2.417178821,"remaining_time":0.7633196276},
{"learn":[0.2782713347],"iteration":76,"passed_time":2.450581444,"remaining_time":0.7319918599},
{"learn":[0.2761240731],"iteration":77,"passed_time":2.482038153,"remaining_time":0.7000620432},
{"learn":[0.2748859008],"iteration":78,"passed_time":2.514587669,"remaining_time":0.6684346968},
{"learn":[0.2737500839],"iteration":79,"passed_time":2.547616155,"remaining_time":0.6369040386},
{"learn":[0.2721895511],"iteration":80,"passed_time":2.579894787,"remaining_time":0.6051605055},
{"learn":[0.2707731156],"iteration":81,"passed_time":2.612765219,"remaining_time":0.5735338286},
{"learn":[0.2688997339],"iteration":82,"passed_time":2.646316469,"remaining_time":0.5420166261},
{"learn":[0.2679901897],"iteration":83,"passed_time":2.678784456,"remaining_time":0.5102446584},
{"learn":[0.2666290407],"iteration":84,"passed_time":2.711388525,"remaining_time":0.4784803279},
{"learn":[0.2658314955],"iteration":85,"passed_time":2.744887325,"remaining_time":0.4468421227},
{"learn":[0.2641556237],"iteration":86,"passed_time":2.79094229,"remaining_time":0.4170373536},
{"learn":[0.2629416394],"iteration":87,"passed_time":2.863965788,"remaining_time":0.3905407893},
{"learn":[0.262289767],"iteration":88,"passed_time":2.913117409,"remaining_time":0.3600482191},
{"learn":[0.2602764482],"iteration":89,"passed_time":2.945710326,"remaining_time":0.3273011473},
{"learn":[0.2591793732],"iteration":90,"passed_time":2.978618642,"remaining_time":0.2945886569},
{"learn":[0.2581032086],"iteration":91,"passed_time":3.010616597,"remaining_time":0.2617927475},
{"learn":[0.2563472092],"iteration":92,"passed_time":3.041714224,"remaining_time":0.2289462319},
{"learn":[0.254928162],"iteration":93,"passed_time":3.074059899,"remaining_time":0.1962165893},
{"learn":[0.2536112365],"iteration":94,"passed_time":3.105833137,"remaining_time":0.1634649019},
{"learn":[0.2529743852],"iteration":95,"passed_time":3.138919528,"remaining_time":0.1307883137},
{"learn":[0.2519357334],"iteration":96,"passed_time":3.171690495,"remaining_time":0.09809352047},
{"learn":[0.2509942574],"iteration":97,"passed_time":3.204684584,"remaining_time":0.0654017262},
{"learn":[0.249451495],"iteration":98,"passed_time":3.236860384,"remaining_time":0.03269555943},
{"learn":[0.2479571933],"iteration":99,"passed_time":3.269800733,"remaining_time":0}
]}